{
  "version": 2,
  "smokeSample": [
    { "title": "斗破苍穹", "bucket": "classic", "weight": 1.0 },
    { "title": "诡秘之主", "bucket": "qidian", "weight": 1.0 },
    { "title": "大奉打更人", "bucket": "qidian", "weight": 1.0 },
    { "title": "凡人修仙传", "bucket": "classic", "weight": 1.0 },
    { "title": "我在精神病院学斩神", "bucket": "fanqie", "weight": 1.0 },
    { "title": "十日终焉", "bucket": "fanqie", "weight": 1.0 },
    { "title": "我不是戏神", "bucket": "fanqie", "weight": 1.0 },
    { "title": "异兽迷城", "bucket": "fanqie", "weight": 1.0 },
    { "title": "剑来", "bucket": "classic", "weight": 1.0 },
    { "title": "雪中悍刀行", "bucket": "classic", "weight": 1.0 }
  ],
  "rareExpansionSample": [
    { "title": "逍遥小散仙", "bucket": "rare", "weight": 1.0 },
    { "title": "琼明神女录", "bucket": "rare", "weight": 1.0 },
    { "title": "六朝清羽记", "bucket": "rare", "weight": 1.0 },
    { "title": "仙子的修行", "bucket": "rare", "weight": 1.0 }
  ],
  "selectionSample": [
    { "title": "斗破苍穹", "bucket": "classic", "weight": 1.0 },
    { "title": "凡人修仙传", "bucket": "classic", "weight": 1.0 },
    { "title": "剑来", "bucket": "classic", "weight": 1.0 },
    { "title": "雪中悍刀行", "bucket": "classic", "weight": 1.0 },
    { "title": "庆余年", "bucket": "classic", "weight": 0.9 },
    { "title": "全职高手", "bucket": "classic", "weight": 0.8 },
    { "title": "斗罗大陆", "bucket": "classic", "weight": 0.8 },
    { "title": "吞噬星空", "bucket": "classic", "weight": 0.8 },
    { "title": "诡秘之主", "bucket": "qidian", "weight": 1.0 },
    { "title": "大奉打更人", "bucket": "qidian", "weight": 1.0 },
    { "title": "宿命之环", "bucket": "qidian", "weight": 0.9 },
    { "title": "灵境行者", "bucket": "qidian", "weight": 0.9 },
    { "title": "赤心巡天", "bucket": "qidian", "weight": 0.8 },
    { "title": "深海余烬", "bucket": "qidian", "weight": 0.8 },
    { "title": "玄鉴仙族", "bucket": "qidian", "weight": 0.7 },
    { "title": "我在精神病院学斩神", "bucket": "fanqie", "weight": 1.0 },
    { "title": "十日终焉", "bucket": "fanqie", "weight": 1.0 },
    { "title": "我不是戏神", "bucket": "fanqie", "weight": 1.0 },
    { "title": "异兽迷城", "bucket": "fanqie", "weight": 1.0 },
    { "title": "开局地摊卖大力", "bucket": "fanqie", "weight": 0.8 },
    { "title": "从红月开始", "bucket": "breadth", "weight": 0.8 },
    { "title": "从姑获鸟开始", "bucket": "breadth", "weight": 0.7 },
    { "title": "这个明星很想退休", "bucket": "breadth", "weight": 0.7 },
    { "title": "我有一座恐怖屋", "bucket": "breadth", "weight": 0.7 },
    { "title": "我的治愈系游戏", "bucket": "breadth", "weight": 0.7 },
    { "title": "道诡异仙", "bucket": "breadth", "weight": 0.7 },
    { "title": "剑烛大荒", "bucket": "rare", "weight": 0.9 },
    { "title": "凡戒窃灵", "bucket": "rare", "weight": 0.8 },
    { "title": "六朝清羽记", "bucket": "rare", "weight": 0.8 },
    { "title": "逍遙小散仙", "bucket": "rare", "weight": 0.8 },
    { "title": "琼明神女录", "bucket": "rare", "weight": 0.8 },
    { "title": "庄老邪修仙传", "bucket": "rare", "weight": 0.8 },
    { "title": "围城", "bucket": "published", "weight": 0.7 },
    { "title": "活着", "bucket": "published", "weight": 0.7 },
    { "title": "平凡的世界", "bucket": "published", "weight": 0.7 },
    { "title": "白鹿原", "bucket": "published", "weight": 0.7 },
    { "title": "三体", "bucket": "published", "weight": 0.8 },
    { "title": "许三观卖血记", "bucket": "published", "weight": 0.6 },
    { "title": "鬼吹灯", "bucket": "category", "weight": 0.7 },
    { "title": "明朝那些事儿", "bucket": "category", "weight": 0.7 }
  ]
}
